{"@context":"https://schema.org","@graph":[{"@type":"Organization","@id":"https://dorastable.com/#organization","name":"Dora's Table","url":"https://dorastable.com/","sameAs":["https://www.facebook.com/drstable","http://instagram.com/dorastable","http://pinterest.com/dorastable","https://twitter.com/dorastable"],"logo":{"@type":"ImageObject","@id":"https://dorastable.com/#logo","inLanguage":"en-US","url":"https://dorastable.com/wp-content/uploads/2020/10/logo.png","contentUrl":"https://dorastable.com/wp-content/uploads/2020/10/logo.png","width":1200,"height":1200,"caption":"Dora's Table"},"image":{"@id":"https://dorastable.com/#logo"}},{"@type":"WebSite","@id":"https://dorastable.com/#website","url":"https://dorastable.com/","name":"Dora&#039;s Table","description":"Mexican Gone Vegan","publisher":{"@id":"https://dorastable.com/#organization"},"potentialAction":[{"@type":"SearchAction","target":{"@type":"EntryPoint","urlTemplate":"https://dorastable.com/?s={search_term_string}"},"query-input":"required name=search_term_string"}],"inLanguage":"en-US"},{"@type":"ImageObject","@id":"https://dorastable.com/vegan-sopa-seca-de-fideo/#primaryimage","inLanguage":"en-US","url":"https://dorastable.com/wp-content/uploads/2020/09/sopa-fideo-9.jpg","contentUrl":"https://dorastable.com/wp-content/uploads/2020/09/sopa-fideo-9.jpg","width":1200,"height":795,"caption":"sopa seca de fideo in a bright blue colored plate"},{"@type":"WebPage","@id":"https://dorastable.com/vegan-sopa-seca-de-fideo/#webpage","url":"https://dorastable.com/vegan-sopa-seca-de-fideo/","name":"Vegan Sopa Seca de Fideo &laquo; Dora&#039;s Table","isPartOf":{"@id":"https://dorastable.com/#website"},"primaryImageOfPage":{"@id":"https://dorastable.com/vegan-sopa-seca-de-fideo/#primaryimage"},"datePublished":"2020-09-12T14:30:08+00:00","dateModified":"2021-02-27T02:01:47+00:00","breadcrumb":{"@id":"https://dorastable.com/vegan-sopa-seca-de-fideo/#breadcrumb"},"inLanguage":"en-US","potentialAction":[{"@type":"ReadAction","target":["https://dorastable.com/vegan-sopa-seca-de-fideo/"]}]},{"@type":"BreadcrumbList","@id":"https://dorastable.com/vegan-sopa-seca-de-fideo/#breadcrumb","itemListElement":[{"@type":"ListItem","position":1,"name":"Home","item":"https://dorastable.com/"},{"@type":"ListItem","position":2,"name":"Vegan Mexican Recipes","item":"https://dorastable.com/category/veganmexican/"},{"@type":"ListItem","position":3,"name":"Vegan Sopa Seca de Fideo"}]},{"@type":"Article","@id":"https://dorastable.com/vegan-sopa-seca-de-fideo/#article","isPartOf":{"@id":"https://dorastable.com/vegan-sopa-seca-de-fideo/#webpage"},"author":{"@id":"https://dorastable.com/#/schema/person/be223c29e5b4a775ec11d3a64f52e2a1"},"headline":"Vegan Sopa Seca de Fideo","datePublished":"2020-09-12T14:30:08+00:00","dateModified":"2021-02-27T02:01:47+00:00","wordCount":592,"commentCount":0,"publisher":{"@id":"https://dorastable.com/#organization"},"image":{"@id":"https://dorastable.com/vegan-sopa-seca-de-fideo/#primaryimage"},"thumbnailUrl":"https://dorastable.com/wp-content/uploads/2020/09/sopa-fideo-9.jpg","keywords":["fideo","garlic","noodles","onion","tomato"],"articleSection":["Main Course","Pasta","Vegan Mexican Recipes","WFPB"],"inLanguage":"en-US","potentialAction":[{"@type":"CommentAction","name":"Comment","target":["https://dorastable.com/vegan-sopa-seca-de-fideo/#respond"]}]},{"@type":"Person","@id":"https://dorastable.com/#/schema/person/be223c29e5b4a775ec11d3a64f52e2a1","name":"Dora S.","image":{"@type":"ImageObject","@id":"https://dorastable.com/#personlogo","inLanguage":"en-US","url":"https://secure.gravatar.com/avatar/ca6233450e4444e1b97627c512c913b8?s=96&d=mm&r=g","contentUrl":"https://secure.gravatar.com/avatar/ca6233450e4444e1b97627c512c913b8?s=96&d=mm&r=g","caption":"Dora S."},"description":"Dora is the founder, recipe developer, and photographer at Dora's Table and Mi Mero Mole. Born and raised in Mexico and a graduate of the Culinary Institute of America in New York, she adopted a vegan (plant-based) diet to take control of her health.","sameAs":["https://dorastable.com/about/about-me/"],"url":"https://dorastable.com/author/dora-l-stonegmail-com/"},{"@context":"http://schema.org/","@type":"Recipe","name":"Sopa Seca de Fideo","author":{"@type":"Person","name":"Dora S."},"description":"A spicy chipotle tomato noodle casserole. A distant cousin of sopa de fideo.","datePublished":"2020-09-12T07:30:08+00:00","image":["https://dorastable.com/wp-content/uploads/2020/09/sopa-fideo-9.jpg","https://dorastable.com/wp-content/uploads/2020/09/sopa-fideo-9-500x500.jpg","https://dorastable.com/wp-content/uploads/2020/09/sopa-fideo-9-500x375.jpg","https://dorastable.com/wp-content/uploads/2020/09/sopa-fideo-9-480x270.jpg"],"recipeYield":["4","4 servings"],"totalTime":"PT30M","recipeIngredient":["8 oz. Fideo noodles (or thin spaghetti broken into 1 inch pieces)","1 can Diced tomatoes","1/2  White onion (chopped)","2 cloves Garlic (peeled)","1  Chipotle pepper in adobo","1 tsp. Dry oregano","1 ¼ cups Small diced (zucchini)","1 ½ cup Vegetable broth","Almond Crema","¼ cup Chopped cilantro","1   Avocado, sliced"],"recipeInstructions":[{"@type":"HowToStep","text":"Place the diced tomatoes, chipotle pepper, onion, garlic, and 1 cup of broth and process until smooth. Set aside.","name":"Place the diced tomatoes, chipotle pepper, onion, garlic, and 1 cup of broth and process until smooth. Set aside.","url":"https://dorastable.com/vegan-sopa-seca-de-fideo/#wprm-recipe-8257-step-0-0"},{"@type":"HowToStep","text":"Set a large pot to medium heat. Add noodles and dry toast the until golden brown. Add tomato broth and let simmer, stirring constantly, until the tomato broth turns a deep red color about 2 minutes. Add zucchini, oregano, and remaining ½ cup of broth.","name":"Set a large pot to medium heat. Add noodles and dry toast the until golden brown. Add tomato broth and let simmer, stirring constantly, until the tomato broth turns a deep red color about 2 minutes. Add zucchini, oregano, and remaining ½ cup of broth.","url":"https://dorastable.com/vegan-sopa-seca-de-fideo/#wprm-recipe-8257-step-0-1"},{"@type":"HowToStep","text":"Turn heat to low, and continue simmering and stirring until the noodles and zucchini are tender, about 10- 12 minutes. Season to taste","name":"Turn heat to low, and continue simmering and stirring until the noodles and zucchini are tender, about 10- 12 minutes. Season to taste","url":"https://dorastable.com/vegan-sopa-seca-de-fideo/#wprm-recipe-8257-step-0-2"},{"@type":"HowToStep","text":"While the noodles are simmering, make your almond crema.","name":"While the noodles are simmering, make your almond crema.","url":"https://dorastable.com/vegan-sopa-seca-de-fideo/#wprm-recipe-8257-step-0-3"},{"@type":"HowToStep","text":"If there is too much liquid in your noodles let them sit for 5 minutes and let the pasta absorb the excess moisture or if there is not enough liquid you can add a","name":"If there is too much liquid in your noodles let them sit for 5 minutes and let the pasta absorb the excess moisture or if there is not enough liquid you can add a","url":"https://dorastable.com/vegan-sopa-seca-de-fideo/#wprm-recipe-8257-step-0-4"},{"@type":"HowToStep","text":"Place noodles on a serving dish and drizzle the almond crema on the noodles, sprinkle with chopped cilantro, and sliced of avocado.","name":"Place noodles on a serving dish and drizzle the almond crema on the noodles, sprinkle with chopped cilantro, and sliced of avocado.","url":"https://dorastable.com/vegan-sopa-seca-de-fideo/#wprm-recipe-8257-step-0-5"}],"aggregateRating":{"@type":"AggregateRating","ratingValue":"5","ratingCount":"1"},"recipeCategory":["Side Dish"],"recipeCuisine":["Mexican"],"keywords":"casserole, mexican, sopa seca de fideo, vega sopa seca de fideo, vegan","nutrition":{"@type":"NutritionInformation","servingSize":"1 serving","calories":"331 kcal","carbohydrateContent":"56 g","proteinContent":"10 g","fatContent":"9 g","saturatedFatContent":"1 g","sodiumContent":"574 mg","fiberContent":"7 g","sugarContent":"7 g"},"@id":"https://dorastable.com/vegan-sopa-seca-de-fideo/#recipe","isPartOf":{"@id":"https://dorastable.com/vegan-sopa-seca-de-fideo/#article"},"mainEntityOfPage":"https://dorastable.com/vegan-sopa-seca-de-fideo/#webpage"}]}