{"@context":"https://schema.org","@graph":[{"@type":"WebSite","@id":"https://thevietvegan.com/#website","url":"https://thevietvegan.com/","name":"The Viet Vegan","description":"Vegan. Feminist. Nerd.","publisher":{"@id":"https://thevietvegan.com/#/schema/person/32db954312f993c7607670eba9ef6c3e"},"potentialAction":[{"@type":"SearchAction","target":{"@type":"EntryPoint","urlTemplate":"https://thevietvegan.com/?s={search_term_string}"},"query-input":"required name=search_term_string"}],"inLanguage":"en-US"},{"@type":"ImageObject","@id":"https://thevietvegan.com/vegan-crispy-baked-soy-bites/#primaryimage","inLanguage":"en-US","url":"https://thevietvegan.com/wp-content/uploads/2015/05/vegan-baked-soy-bites-hero-v-scaled.jpg","contentUrl":"https://thevietvegan.com/wp-content/uploads/2015/05/vegan-baked-soy-bites-hero-v-scaled.jpg","width":2592,"height":3888,"caption":"Vegan Baked Soy Bites | The Viet Vegan | Crunchy, healthier alternatives to fried finger food. [ v e g a n ]"},{"@type":"WebPage","@id":"https://thevietvegan.com/vegan-crispy-baked-soy-bites/#webpage","url":"https://thevietvegan.com/vegan-crispy-baked-soy-bites/","name":"Vegan Crispy Baked Soy Bites - The Viet Vegan","isPartOf":{"@id":"https://thevietvegan.com/#website"},"primaryImageOfPage":{"@id":"https://thevietvegan.com/vegan-crispy-baked-soy-bites/#primaryimage"},"datePublished":"2015-05-26T12:00:45+00:00","dateModified":"2020-11-11T07:22:18+00:00","description":"...otherwise you'll have sad, dry soy bites instead of tender, juicy nuggets of flavour that you can dip in avocado cream.","breadcrumb":{"@id":"https://thevietvegan.com/vegan-crispy-baked-soy-bites/#breadcrumb"},"inLanguage":"en-US","potentialAction":[{"@type":"ReadAction","target":["https://thevietvegan.com/vegan-crispy-baked-soy-bites/"]}]},{"@type":"BreadcrumbList","@id":"https://thevietvegan.com/vegan-crispy-baked-soy-bites/#breadcrumb","itemListElement":[{"@type":"ListItem","position":1,"name":"Home","item":"https://thevietvegan.com/"},{"@type":"ListItem","position":2,"name":"Vegan Crispy Baked Soy Bites"}]},{"@type":"Article","@id":"https://thevietvegan.com/vegan-crispy-baked-soy-bites/#article","isPartOf":{"@id":"https://thevietvegan.com/vegan-crispy-baked-soy-bites/#webpage"},"author":{"@id":"https://thevietvegan.com/#/schema/person/32db954312f993c7607670eba9ef6c3e"},"headline":"Vegan Crispy Baked Soy Bites","datePublished":"2015-05-26T12:00:45+00:00","dateModified":"2020-11-11T07:22:18+00:00","mainEntityOfPage":{"@id":"https://thevietvegan.com/vegan-crispy-baked-soy-bites/#webpage"},"wordCount":1071,"commentCount":7,"publisher":{"@id":"https://thevietvegan.com/#/schema/person/32db954312f993c7607670eba9ef6c3e"},"image":{"@id":"https://thevietvegan.com/vegan-crispy-baked-soy-bites/#primaryimage"},"thumbnailUrl":"https://thevietvegan.com/wp-content/uploads/2015/05/vegan-baked-soy-bites-hero-v-scaled.jpg","keywords":["baked","bites","soy","vegan"],"articleSection":["Appetizers &amp; Sides","Snacks","Vegan recipes"],"inLanguage":"en-US","potentialAction":[{"@type":"CommentAction","name":"Comment","target":["https://thevietvegan.com/vegan-crispy-baked-soy-bites/#respond"]}]},{"@type":["Person","Organization"],"@id":"https://thevietvegan.com/#/schema/person/32db954312f993c7607670eba9ef6c3e","name":"Lisa Le","logo":{"@id":"https://thevietvegan.com/#personlogo"},"description":"Lisa is the thirty-something, nerdy, procrastinating, feminist blogger and photographer behind The Viet Vegan. She loves spicy foods, noodles, and food in bowls.","sameAs":["https://www.thevietvegan.com","http://www.facebook.com/thevietvegan","https://twitter.com/thevietvegan"],"url":"https://thevietvegan.com/author/the-viet-vegan/"}]}