{"@context":"https://schema.org","@graph":[{"@type":"WebSite","@id":"https://thevietvegan.com/#website","url":"https://thevietvegan.com/","name":"The Viet Vegan","description":"Vegan. Feminist. Nerd.","publisher":{"@id":"https://thevietvegan.com/#/schema/person/32db954312f993c7607670eba9ef6c3e"},"potentialAction":[{"@type":"SearchAction","target":{"@type":"EntryPoint","urlTemplate":"https://thevietvegan.com/?s={search_term_string}"},"query-input":"required name=search_term_string"}],"inLanguage":"en-US"},{"@type":"ImageObject","@id":"https://thevietvegan.com/natural-red-velvet-cupcakes-made-with-beets/#primaryimage","inLanguage":"en-US","url":"https://thevietvegan.com/wp-content/uploads/2013/06/IMG_1317W.jpg","contentUrl":"https://thevietvegan.com/wp-content/uploads/2013/06/IMG_1317W.jpg","width":600,"height":800,"caption":"Natural Red Velvet Cupcakes | alimentageuse.com - Naturally made, vegan with no artificial food colouring! #cupcakes #vegan #beets"},{"@type":"WebPage","@id":"https://thevietvegan.com/natural-red-velvet-cupcakes-made-with-beets/#webpage","url":"https://thevietvegan.com/natural-red-velvet-cupcakes-made-with-beets/","name":"Natural Red Velvet Cupcakes made with Beets - The Viet Vegan","isPartOf":{"@id":"https://thevietvegan.com/#website"},"primaryImageOfPage":{"@id":"https://thevietvegan.com/natural-red-velvet-cupcakes-made-with-beets/#primaryimage"},"datePublished":"2013-06-14T05:39:55+00:00","dateModified":"2020-10-24T18:33:54+00:00","breadcrumb":{"@id":"https://thevietvegan.com/natural-red-velvet-cupcakes-made-with-beets/#breadcrumb"},"inLanguage":"en-US","potentialAction":[{"@type":"ReadAction","target":["https://thevietvegan.com/natural-red-velvet-cupcakes-made-with-beets/"]}]},{"@type":"BreadcrumbList","@id":"https://thevietvegan.com/natural-red-velvet-cupcakes-made-with-beets/#breadcrumb","itemListElement":[{"@type":"ListItem","position":1,"name":"Home","item":"https://thevietvegan.com/"},{"@type":"ListItem","position":2,"name":"Natural Red Velvet Cupcakes made with Beets"}]},{"@type":"Article","@id":"https://thevietvegan.com/natural-red-velvet-cupcakes-made-with-beets/#article","isPartOf":{"@id":"https://thevietvegan.com/natural-red-velvet-cupcakes-made-with-beets/#webpage"},"author":{"@id":"https://thevietvegan.com/#/schema/person/32db954312f993c7607670eba9ef6c3e"},"headline":"Natural Red Velvet Cupcakes made with Beets","datePublished":"2013-06-14T05:39:55+00:00","dateModified":"2020-10-24T18:33:54+00:00","mainEntityOfPage":{"@id":"https://thevietvegan.com/natural-red-velvet-cupcakes-made-with-beets/#webpage"},"wordCount":889,"commentCount":195,"publisher":{"@id":"https://thevietvegan.com/#/schema/person/32db954312f993c7607670eba9ef6c3e"},"image":{"@id":"https://thevietvegan.com/natural-red-velvet-cupcakes-made-with-beets/#primaryimage"},"thumbnailUrl":"https://thevietvegan.com/wp-content/uploads/2013/06/IMG_1317W.jpg","keywords":["beets","cheese","cream","cupcakes","dairy-free","egg-free","eggless","icing","red velvet","vegan","vegetarian"],"articleSection":["Baking","Dessert","Vegan recipes"],"inLanguage":"en-US","potentialAction":[{"@type":"CommentAction","name":"Comment","target":["https://thevietvegan.com/natural-red-velvet-cupcakes-made-with-beets/#respond"]}]},{"@type":["Person","Organization"],"@id":"https://thevietvegan.com/#/schema/person/32db954312f993c7607670eba9ef6c3e","name":"Lisa Le","logo":{"@id":"https://thevietvegan.com/#personlogo"},"description":"Lisa is the thirty-something, nerdy, procrastinating, feminist blogger and photographer behind The Viet Vegan. She loves spicy foods, noodles, and food in bowls.","sameAs":["https://www.thevietvegan.com","http://www.facebook.com/thevietvegan","https://twitter.com/thevietvegan"],"url":"https://thevietvegan.com/author/the-viet-vegan/"}]}