{"@context":"https://schema.org","@graph":[{"@type":"WebSite","@id":"https://thevietvegan.com/#website","url":"https://thevietvegan.com/","name":"The Viet Vegan","description":"Vegan. Feminist. Nerd.","publisher":{"@id":"https://thevietvegan.com/#/schema/person/32db954312f993c7607670eba9ef6c3e"},"potentialAction":[{"@type":"SearchAction","target":{"@type":"EntryPoint","urlTemplate":"https://thevietvegan.com/?s={search_term_string}"},"query-input":"required name=search_term_string"}],"inLanguage":"en-US"},{"@type":"ImageObject","@id":"https://thevietvegan.com/vegan-caesar-salad-dressing/#primaryimage","inLanguage":"en-US","url":"https://thevietvegan.com/wp-content/uploads/2015/07/vegan-caesar-salad-hero-v-w-web.jpg","contentUrl":"https://thevietvegan.com/wp-content/uploads/2015/07/vegan-caesar-salad-hero-v-w-web.jpg","width":1024,"height":1536,"caption":"Vegan Caesar Salad Dressing | The Viet Vegan"},{"@type":"WebPage","@id":"https://thevietvegan.com/vegan-caesar-salad-dressing/#webpage","url":"https://thevietvegan.com/vegan-caesar-salad-dressing/","name":"Vegan Caesar Salad Dressing - The Viet Vegan","isPartOf":{"@id":"https://thevietvegan.com/#website"},"primaryImageOfPage":{"@id":"https://thevietvegan.com/vegan-caesar-salad-dressing/#primaryimage"},"datePublished":"2015-07-03T15:39:08+00:00","dateModified":"2020-09-30T20:32:07+00:00","breadcrumb":{"@id":"https://thevietvegan.com/vegan-caesar-salad-dressing/#breadcrumb"},"inLanguage":"en-US","potentialAction":[{"@type":"ReadAction","target":["https://thevietvegan.com/vegan-caesar-salad-dressing/"]}]},{"@type":"BreadcrumbList","@id":"https://thevietvegan.com/vegan-caesar-salad-dressing/#breadcrumb","itemListElement":[{"@type":"ListItem","position":1,"name":"Home","item":"https://thevietvegan.com/"},{"@type":"ListItem","position":2,"name":"Vegan Caesar Salad Dressing"}]},{"@type":"Article","@id":"https://thevietvegan.com/vegan-caesar-salad-dressing/#article","isPartOf":{"@id":"https://thevietvegan.com/vegan-caesar-salad-dressing/#webpage"},"author":{"@id":"https://thevietvegan.com/#/schema/person/32db954312f993c7607670eba9ef6c3e"},"headline":"Vegan Caesar Salad Dressing","datePublished":"2015-07-03T15:39:08+00:00","dateModified":"2020-09-30T20:32:07+00:00","mainEntityOfPage":{"@id":"https://thevietvegan.com/vegan-caesar-salad-dressing/#webpage"},"wordCount":1050,"commentCount":4,"publisher":{"@id":"https://thevietvegan.com/#/schema/person/32db954312f993c7607670eba9ef6c3e"},"image":{"@id":"https://thevietvegan.com/vegan-caesar-salad-dressing/#primaryimage"},"thumbnailUrl":"https://thevietvegan.com/wp-content/uploads/2015/07/vegan-caesar-salad-hero-v-w-web.jpg","keywords":["caesar","dressing","online blog con","salad","vegan"],"articleSection":["Appetizers &amp; Sides","Condiments &amp; Sauces","Gluten-Free","Lunch","Vegan recipes"],"inLanguage":"en-US","potentialAction":[{"@type":"CommentAction","name":"Comment","target":["https://thevietvegan.com/vegan-caesar-salad-dressing/#respond"]}]},{"@type":["Person","Organization"],"@id":"https://thevietvegan.com/#/schema/person/32db954312f993c7607670eba9ef6c3e","name":"Lisa Le","logo":{"@id":"https://thevietvegan.com/#personlogo"},"description":"Lisa is the thirty-something, nerdy, procrastinating, feminist blogger and photographer behind The Viet Vegan. She loves spicy foods, noodles, and food in bowls.","sameAs":["https://www.thevietvegan.com","http://www.facebook.com/thevietvegan","https://twitter.com/thevietvegan"],"url":"https://thevietvegan.com/author/the-viet-vegan/"}]}