{"@context":"https://schema.org","@graph":[{"@type":"WebSite","@id":"https://thevietvegan.com/#website","url":"https://thevietvegan.com/","name":"The Viet Vegan","description":"Vegan. Feminist. Nerd.","publisher":{"@id":"https://thevietvegan.com/#/schema/person/32db954312f993c7607670eba9ef6c3e"},"potentialAction":[{"@type":"SearchAction","target":{"@type":"EntryPoint","urlTemplate":"https://thevietvegan.com/?s={search_term_string}"},"query-input":"required name=search_term_string"}],"inLanguage":"en-US"},{"@type":"ImageObject","@id":"https://thevietvegan.com/vegan-miso-dulse-onigiri/#primaryimage","inLanguage":"en-US","url":"https://thevietvegan.com/wp-content/uploads/2015/10/vegan-miso-dulse-onigiri-hero-v-w.jpg","contentUrl":"https://thevietvegan.com/wp-content/uploads/2015/10/vegan-miso-dulse-onigiri-hero-v-w.jpg","width":1200,"height":1800,"caption":"Vegan Miso Dulse Onigiri | The Viet Vegan | Japanese versions of \"sandwiches\", onigiri are stuffed rice triangles"},{"@type":"WebPage","@id":"https://thevietvegan.com/vegan-miso-dulse-onigiri/#webpage","url":"https://thevietvegan.com/vegan-miso-dulse-onigiri/","name":"Vegan Miso Dulse Onigiri - The Viet Vegan","isPartOf":{"@id":"https://thevietvegan.com/#website"},"primaryImageOfPage":{"@id":"https://thevietvegan.com/vegan-miso-dulse-onigiri/#primaryimage"},"datePublished":"2015-10-22T14:56:56+00:00","dateModified":"2021-10-04T21:16:12+00:00","description":"I equate these vegan miso dulse onigiri to Japanese versions of sandwiches:Filled rice triangles that are perfect to-go meals that are fun...","breadcrumb":{"@id":"https://thevietvegan.com/vegan-miso-dulse-onigiri/#breadcrumb"},"inLanguage":"en-US","potentialAction":[{"@type":"ReadAction","target":["https://thevietvegan.com/vegan-miso-dulse-onigiri/"]}]},{"@type":"BreadcrumbList","@id":"https://thevietvegan.com/vegan-miso-dulse-onigiri/#breadcrumb","itemListElement":[{"@type":"ListItem","position":1,"name":"Home","item":"https://thevietvegan.com/"},{"@type":"ListItem","position":2,"name":"Vegan Miso Dulse Onigiri"}]},{"@type":"Article","@id":"https://thevietvegan.com/vegan-miso-dulse-onigiri/#article","isPartOf":{"@id":"https://thevietvegan.com/vegan-miso-dulse-onigiri/#webpage"},"author":{"@id":"https://thevietvegan.com/#/schema/person/32db954312f993c7607670eba9ef6c3e"},"headline":"Vegan Miso Dulse Onigiri","datePublished":"2015-10-22T14:56:56+00:00","dateModified":"2021-10-04T21:16:12+00:00","mainEntityOfPage":{"@id":"https://thevietvegan.com/vegan-miso-dulse-onigiri/#webpage"},"wordCount":591,"commentCount":3,"publisher":{"@id":"https://thevietvegan.com/#/schema/person/32db954312f993c7607670eba9ef6c3e"},"image":{"@id":"https://thevietvegan.com/vegan-miso-dulse-onigiri/#primaryimage"},"thumbnailUrl":"https://thevietvegan.com/wp-content/uploads/2015/10/vegan-miso-dulse-onigiri-hero-v-w.jpg","keywords":["dulse","japanese","lunch","miso","onigiri","rice","vegan"],"articleSection":["Asian","Gluten-Free","Lunch","Snacks","Vegan recipes"],"inLanguage":"en-US","potentialAction":[{"@type":"CommentAction","name":"Comment","target":["https://thevietvegan.com/vegan-miso-dulse-onigiri/#respond"]}]},{"@type":["Person","Organization"],"@id":"https://thevietvegan.com/#/schema/person/32db954312f993c7607670eba9ef6c3e","name":"Lisa Le","logo":{"@id":"https://thevietvegan.com/#personlogo"},"description":"Lisa is the thirty-something, nerdy, procrastinating, feminist blogger and photographer behind The Viet Vegan. She loves spicy foods, noodles, and food in bowls.","sameAs":["https://www.thevietvegan.com","http://www.facebook.com/thevietvegan","https://twitter.com/thevietvegan"],"url":"https://thevietvegan.com/author/the-viet-vegan/"}]}