{"@context":"https://schema.org","@graph":[{"@type":"Organization","@id":"https://www.noracooks.com/#organization","name":"Nora Cooks","url":"https://www.noracooks.com/","sameAs":["https://www.facebook.com/noracookswithplants/","https://www.instagram.com/nora_cooks_plant_based/","https://www.pinterest.com/noracooks/"],"logo":{"@type":"ImageObject","@id":"https://www.noracooks.com/#logo","inLanguage":"en-US","url":"https://www.noracooks.com/wp-content/uploads/2017/02/IMG_2427.jpg","contentUrl":"https://www.noracooks.com/wp-content/uploads/2017/02/IMG_2427.jpg","width":1080,"height":720,"caption":"Nora Cooks"},"image":{"@id":"https://www.noracooks.com/#logo"}},{"@type":"WebSite","@id":"https://www.noracooks.com/#website","url":"https://www.noracooks.com/","name":"Nora Cooks","description":"The Food You Love Made Vegan","publisher":{"@id":"https://www.noracooks.com/#organization"},"potentialAction":[{"@type":"SearchAction","target":{"@type":"EntryPoint","urlTemplate":"https://www.noracooks.com/?s={search_term_string}"},"query-input":"required name=search_term_string"}],"inLanguage":"en-US"},{"@type":"ImageObject","@id":"https://www.noracooks.com/vegan-desserts/#primaryimage","inLanguage":"en-US","url":"https://www.noracooks.com/wp-content/uploads/2020/10/sqsq2.jpg","contentUrl":"https://www.noracooks.com/wp-content/uploads/2020/10/sqsq2.jpg","width":800,"height":800,"caption":"square collage of best vegan desserts"},{"@type":"WebPage","@id":"https://www.noracooks.com/vegan-desserts/#webpage","url":"https://www.noracooks.com/vegan-desserts/","name":"Best Vegan Desserts - Nora Cooks","isPartOf":{"@id":"https://www.noracooks.com/#website"},"primaryImageOfPage":{"@id":"https://www.noracooks.com/vegan-desserts/#primaryimage"},"datePublished":"2020-10-23T14:56:07+00:00","dateModified":"2021-09-08T19:24:18+00:00","description":"Here are 50 of the BEST vegan desserts that even non-vegans will love! Plus, these desserts are simple to make, often in 1 bowl!","breadcrumb":{"@id":"https://www.noracooks.com/vegan-desserts/#breadcrumb"},"inLanguage":"en-US","potentialAction":[{"@type":"ReadAction","target":["https://www.noracooks.com/vegan-desserts/"]}]},{"@type":"BreadcrumbList","@id":"https://www.noracooks.com/vegan-desserts/#breadcrumb","itemListElement":[{"@type":"ListItem","position":1,"name":"Home","item":"https://www.noracooks.com/"},{"@type":"ListItem","position":2,"name":"Dessert","item":"https://www.noracooks.com/category/vegan-desserts/"},{"@type":"ListItem","position":3,"name":"Best Vegan Desserts"}]},{"@type":"Article","@id":"https://www.noracooks.com/vegan-desserts/#article","isPartOf":{"@id":"https://www.noracooks.com/vegan-desserts/#webpage"},"author":{"@id":"https://www.noracooks.com/#/schema/person/750d52d3520ab900b00ea775d3b353df"},"headline":"Best Vegan Desserts","datePublished":"2020-10-23T14:56:07+00:00","dateModified":"2021-09-08T19:24:18+00:00","mainEntityOfPage":{"@id":"https://www.noracooks.com/vegan-desserts/#webpage"},"wordCount":1236,"commentCount":22,"publisher":{"@id":"https://www.noracooks.com/#organization"},"image":{"@id":"https://www.noracooks.com/vegan-desserts/#primaryimage"},"thumbnailUrl":"https://www.noracooks.com/wp-content/uploads/2020/10/sqsq2.jpg","keywords":["celebration","chocolate","dessert","holiday","kid-friendly","sweets"],"articleSection":["Dessert","Helpful Guides"],"inLanguage":"en-US","potentialAction":[{"@type":"CommentAction","name":"Comment","target":["https://www.noracooks.com/vegan-desserts/#respond"]}]},{"@type":"Person","@id":"https://www.noracooks.com/#/schema/person/750d52d3520ab900b00ea775d3b353df","name":"Nora","sameAs":["http://www.plantbasedfamily.com","https://www.facebook.com/Plant-Strong-Family-1851071811838022/","https://www.pinterest.com/ntaylor2013/"]}]}